README.rst
setup.py
kafkaka/__init__.py
kafkaka/__init__.pyc
kafkaka/bstruct.py
kafkaka/bstruct.pyc
kafkaka/client.py
kafkaka/client.pyc
kafkaka/conn.py
kafkaka/conn.pyc
kafkaka/define.py
kafkaka/define.pyc
kafkaka/gevent_patch.py
kafkaka/gevent_patch.pyc
kafkaka/protocol.py
kafkaka/protocol.pyc
kafkaka/tornado_patch.py
kafkaka/tornado_patch.pyc
kafkaka/util.py
kafkaka/util.pyc
kafkaka.egg-info/PKG-INFO
kafkaka.egg-info/SOURCES.txt
kafkaka.egg-info/dependency_links.txt
kafkaka.egg-info/top_level.txt
test/test.py
test/test_autocreate_topics.py
test/test_gevent.py
test/test_gevent_pool_size.py
test/test_tornado.py