Metadata-Version: 1.1
Name: kafkaka
Version: 0.2.7
Summary: Kafka Client with smarter protocol described, support for Gevent and tornado
Home-page: https://github.com/wesdu/kafkaka
Author: Du Wei
Author-email: pandorid@gmail.com
License: Apache License 2.0
Keywords: Kafka,gevent,tornado,client
Platform: UNKNOWN
Classifier: Intended Audience :: Developers
Classifier: License :: OSI Approved :: Apache Software License
Classifier: Operating System :: OS Independent
Classifier: Natural Language :: English
Classifier: Natural Language :: Chinese (Simplified)
Classifier: Natural Language :: Chinese (Traditional)
Classifier: Programming Language :: Python
Classifier: Programming Language :: Python :: 2
Classifier: Programming Language :: Python :: 2.7
Classifier: Topic :: Software Development :: Libraries :: Python Modules
Requires: gevent
Requires: tornado
